bitslice/__init__.py
bitslice/bitslice.py
bitslice-0.3.0.dist-info/LICENSE
bitslice-0.3.0.dist-info/WHEEL
bitslice-0.3.0.dist-info/METADATA
bitslice-0.3.0.dist-info/RECORD
