Metadata-Version: 2.1
Name: bitslice
Version: 0.3.0
Summary: Verilog-like bitvector slicing
Home-page: https://github.com/zegervdv/bitslice
License: MIT
Author: Zeger Van de Vannet
Author-email: zegervdv@me.com
Requires-Python: >=3.7,<4.0
Classifier: License :: OSI Approved :: MIT License
Classifier: Programming Language :: Python :: 3
Classifier: Programming Language :: Python :: 3.7
Classifier: Programming Language :: Python :: 3.8
